groundero/__init__.py
groundero/build.py
groundero/citation_retrieval.py
groundero/cli.py
groundero/config.py
groundero/document_store.py
groundero/groundero_core.py
groundero/install.py
groundero/py.typed
groundero/query.py
groundero/zotero_client.py
groundero-0.1.0.dist-info/METADATA
groundero-0.1.0.dist-info/WHEEL
groundero-0.1.0.dist-info/entry_points.txt
groundero-0.1.0.dist-info/licenses/LICENSE
groundero-0.1.0.dist-info/RECORD
