Metadata-Version: 2.4
Name: groundero
Version: 0.1.0
Summary: Visual grounding search for academic papers with Zotero integration
Project-URL: Homepage, https://github.com/rodrigodzf/groundero
Project-URL: Repository, https://github.com/rodrigodzf/groundero.git
Project-URL: Documentation, https://github.com/rodrigodzf/groundero#readme
Project-URL: Issues, https://github.com/rodrigodzf/groundero/issues
Author-email: Rodrigo Diaz <rodrigodzf@gmail.com>
License: MIT
License-File: LICENSE
Keywords: academic-search,ai,docling,langchain,pdf,research,visual-grounding,zotero
Classifier: Development Status :: 3 - Alpha
Classifier: Intended Audience :: Developers
Classifier: Intended Audience :: Science/Research
Classifier: License :: OSI Approved :: MIT License
Classifier: Operating System :: OS Independent
Classifier: Programming Language :: Python :: 3
Classifier: Programming Language :: Python :: 3.11
Classifier: Programming Language :: Python :: 3.12
Classifier: Topic :: Scientific/Engineering :: Artificial Intelligence
Classifier: Topic :: Software Development :: Libraries :: Python Modules
Classifier: Topic :: Text Processing :: Indexing
Requires-Python: >=3.11
Requires-Dist: docling>=2.47.0
Requires-Dist: ipykernel>=6.30.1
Requires-Dist: langchain-core>=0.3.74
Requires-Dist: langchain-docling>=1.0.0
Requires-Dist: langchain-google-genai>=2.1.9
Requires-Dist: langchain-huggingface>=0.3.1
Requires-Dist: langchain-milvus>=0.2.1
Requires-Dist: langchain>=0.3.27
Requires-Dist: platformdirs>=4.3.8
Requires-Dist: python-dotenv>=1.1.1
Requires-Dist: pyzotero>=1.6.11
Requires-Dist: rich>=14.1.0
Requires-Dist: sentence-transformers>=5.1.0
Requires-Dist: sqlmodel>=0.0.24
Provides-Extra: dev
Requires-Dist: black>=23.0; extra == 'dev'
Requires-Dist: pytest>=7.0; extra == 'dev'
Requires-Dist: ruff>=0.1.0; extra == 'dev'
Requires-Dist: ty>=0.0.1a19; extra == 'dev'
